cryosparc2/__init__.py
cryosparc2/bibtex.py
cryosparc2/constants.py
cryosparc2/cryosparc2_logo.png
cryosparc2/protocols.conf
cryosparc2/utils.py
cryosparc2/wizards.py
cryosparc2/convert/__init__.py
cryosparc2/convert/convert.py
cryosparc2/convert/cs2Start.py
cryosparc2/convert/dataimport.py
cryosparc2/protocols/__init__.py
cryosparc2/protocols/protocol_base.py
cryosparc2/protocols/protocol_cryosparc2d.py
cryosparc2/protocols/protocol_cryosparc_3D_classification.py
cryosparc2/protocols/protocol_cryosparc_3D_flex_data_prepare.py
cryosparc2/protocols/protocol_cryosparc_3D_flex_generator.py
cryosparc2/protocols/protocol_cryosparc_3D_flex_mesh_prepare.py
cryosparc2/protocols/protocol_cryosparc_3D_flex_reconstruction.py
cryosparc2/protocols/protocol_cryosparc_3D_flex_training.py
cryosparc2/protocols/protocol_cryosparc_3d_variability.py
cryosparc2/protocols/protocol_cryosparc_3d_variability_display.py
cryosparc2/protocols/protocol_cryosparc_ab.py
cryosparc2/protocols/protocol_cryosparc_blob_picker.py
cryosparc2/protocols/protocol_cryosparc_global_ctf_refinement.py
cryosparc2/protocols/protocol_cryosparc_helical_refinement.py
cryosparc2/protocols/protocol_cryosparc_homogeneous_reconstruction.py
cryosparc2/protocols/protocol_cryosparc_homogeneous_refine.py
cryosparc2/protocols/protocol_cryosparc_local_ctf_refinement.py
cryosparc2/protocols/protocol_cryosparc_new_3D_classification.py
cryosparc2/protocols/protocol_cryosparc_new_local_refine.py
cryosparc2/protocols/protocol_cryosparc_new_nonuniform_refine.py
cryosparc2/protocols/protocol_cryosparc_part_subtract.py
cryosparc2/protocols/protocol_cryosparc_patch_ctf_estimation.py
cryosparc2/protocols/protocol_cryosparc_sharppening.py
cryosparc2/protocols/protocol_cryosparc_symmetry_expansion.py
cryosparc2/tests/__init__.py
cryosparc2/tests/test_flex.py
cryosparc2/tests/test_protocols_cryosparc2.py
cryosparc2/tests/test_utils.py
cryosparc2/viewers/__init__.py
cryosparc2/viewers/viewer_2Dclassify.py
scipion_em_cryosparc2-4.2.2.dist-info/LICENSE
scipion_em_cryosparc2-4.2.2.dist-info/METADATA
scipion_em_cryosparc2-4.2.2.dist-info/WHEEL
scipion_em_cryosparc2-4.2.2.dist-info/entry_points.txt
scipion_em_cryosparc2-4.2.2.dist-info/top_level.txt
scipion_em_cryosparc2-4.2.2.dist-info/RECORD
