Metadata-Version: 2.1
Name: scipion-em-cryosparc2
Version: 4.2.2
Summary: Plugin to use cryoSPARC2 programs within the Scipion framework
Author-email: Yunior Fonseca <cfonseca@cnb.csic.es>, Szu-Chi Chung <phonchi@stat.sinica.edu.tw>
License: GNU General Public License v3 (GPLv3)
Project-URL: Homepage, https://github.com/scipion-em/scipion-em-cryosparc2
Project-URL: Repository, https://github.com/scipion-em/scipion-em-cryosparc2
Project-URL: Issues, https://github.com/scipion-em/scipion-em-cryosparc2/issues
Keywords: scipion,electron-microscopy,cryo-em,structural-biology,image-processing,scipion-3.0,cryoSPARC
Requires-Python: >=3.8
License-File: LICENSE
Requires-Dist: scipion-em>=3.9.4
Requires-Dist: emtable
Requires-Dist: cryosparc-tools==4.5.0
